artificial_neural_network_model_automation/__init__.py
artificial_neural_network_model_automation/artificial_neural_network_handler.py
artificial_neural_network_model_automation/hyper_parameter_tuning.py
artificial_neural_network_model_automation_helper/__init__.py
artificial_neural_network_model_automation_helper/classification_helper.py
artificial_neural_network_model_automation_helper/decorators.py
artificial_neural_network_model_automation_helper/helper.py
artificial_neural_network_model_automation_helper/make_keras_pickable.py
artificial_neural_network_model_automation_helper/regression_helper.py
artificial_neural_network_model_automation-0.0.3.dist-info/LICENSE
artificial_neural_network_model_automation-0.0.3.dist-info/METADATA
artificial_neural_network_model_automation-0.0.3.dist-info/WHEEL
artificial_neural_network_model_automation-0.0.3.dist-info/top_level.txt
artificial_neural_network_model_automation-0.0.3.dist-info/RECORD
